kafka_schema_registry_admin/__init__.py
kafka_schema_registry_admin/async_schema_registry.py
kafka_schema_registry_admin/client_wrapper/__init__.py
kafka_schema_registry_admin/client_wrapper/async_client.py
kafka_schema_registry_admin/client_wrapper/errors.py
kafka_schema_registry_admin/kafka_schema_registry_admin.py
kafka_schema_registry_admin-0.5.3.dist-info/AUTHORS.rst
kafka_schema_registry_admin-0.5.3.dist-info/LICENSE
kafka_schema_registry_admin-0.5.3.dist-info/METADATA
kafka_schema_registry_admin-0.5.3.dist-info/WHEEL
kafka_schema_registry_admin-0.5.3.dist-info/RECORD
