Metadata-Version: 2.1
Name: kafka-schema-registry-admin
Version: 0.5.3
Summary: Pure HTTP client to manage schemas in Schema Registry
License: Apache-2.0
Author: John Preston
Author-email: john@ews-network.net
Requires-Python: >=3.9,<4.0
Classifier: Development Status :: 2 - Pre-Alpha
Classifier: Intended Audience :: Developers
Classifier: License :: OSI Approved :: Apache Software License
Classifier: Natural Language :: English
Classifier: Programming Language :: Python :: 3
Classifier: Programming Language :: Python :: 3.9
Classifier: Programming Language :: Python :: 3.10
Classifier: Programming Language :: Python :: 3.11
Classifier: Programming Language :: Python :: 3.12
Requires-Dist: httpx (>=0.27.0,<0.28.0)
Requires-Dist: requests (>=2.28.0,<3.0.0)
